mathmind_mcp_server/__init__.py
mathmind_mcp_server/config.py
mathmind_mcp_server/server.py
mathmind_mcp_server/util.py
mathmind_mcp_server/tools/__init__.py
mathmind_mcp_server/tools/fetch_task_by_traceId.py
mathmind_mcp_server/tools/image_2_video.py
mathmind_mcp_server/tools/image_gen_video.py
mathmind_mcp_server/tools/imgPip.py
mathmind_mcp_server/tools/imgPipTask.py
mathmind_mcp_server/tools/imgs2video.py
mathmind_mcp_server/tools/subtitle_dynamic.py
mathmind_mcp_server/tools/video2text.py
mathmind_mcp_server/tools/video2video.py
mathmind_mcp_server/tools/video_cut_random.py
mathmind_mcp_server-0.1.18.dist-info/METADATA
mathmind_mcp_server-0.1.18.dist-info/WHEEL
mathmind_mcp_server-0.1.18.dist-info/entry_points.txt
mathmind_mcp_server-0.1.18.dist-info/RECORD
