Metadata-Version: 2.4
Name: mathmind-mcp-server
Version: 0.1.18
Summary: MCP Server for interacting with Mathmind
Requires-Python: >=3.13
Requires-Dist: fastmcp==2.11.2
Requires-Dist: requests>=2.32.3
Requires-Dist: twine>=6.1.0
